README.rst
setup.py
Flask_HipPocket.egg-info/PKG-INFO
Flask_HipPocket.egg-info/SOURCES.txt
Flask_HipPocket.egg-info/dependency_links.txt
Flask_HipPocket.egg-info/not-zip-safe
Flask_HipPocket.egg-info/requires.txt
Flask_HipPocket.egg-info/top_level.txt
flask_hippocket/__init__.py
flask_hippocket/constants.py
flask_hippocket/pocket.py
flask_hippocket/tasks.py
flask_hippocket/tests/__init__.py
flask_hippocket/tests/mapper.py
flask_hippocket/tests/test_apps/__init__.py
flask_hippocket/tests/test_apps/mapper/__init__.py